test_template_hasuashusauh/__init__.py
test_template_hasuashusauh/py.typed
test_template_hasuashusauh-1.5.0.dist-info/METADATA
test_template_hasuashusauh-1.5.0.dist-info/WHEEL
test_template_hasuashusauh-1.5.0.dist-info/licenses/LICENSE
test_template_hasuashusauh-1.5.0.dist-info/RECORD
