Metadata-Version: 2.1
Name: test-template-hasuashusauh
Version: 1.5.0
Summary: An awesome package is coming soon! 🎉
Project-URL: Homepage, https://github.com/Kludex/test-template-hasuashusauh
Project-URL: Source, https://github.com/Kludex/test-template-hasuashusauh
Project-URL: Twitter, https://twitter.com/marcelotryle
Project-URL: Funding, https://github.com/sponsors/Kludex
Author-email: Marcelo Trylesinski <marcelotryle@email.com>
License-File: LICENSE
Classifier: Development Status :: 3 - Alpha
Classifier: Intended Audience :: Developers
Classifier: License :: OSI Approved :: MIT License
Classifier: Natural Language :: English
Classifier: Operating System :: OS Independent
Classifier: Programming Language :: Python :: 3
Classifier: Programming Language :: Python :: 3 :: Only
Classifier: Programming Language :: Python :: 3.7
Classifier: Programming Language :: Python :: 3.8
Classifier: Programming Language :: Python :: 3.9
Classifier: Programming Language :: Python :: 3.10
Classifier: Programming Language :: Python :: 3.11
Requires-Python: >=3.7
